MANIFEST.in
README.md
setup.py
autocomplete_light/__init__.py
autocomplete_light.egg-info/PKG-INFO
autocomplete_light.egg-info/SOURCES.txt
autocomplete_light.egg-info/dependency_links.txt
autocomplete_light.egg-info/requires.txt
autocomplete_light.egg-info/top_level.txt
autocomplete_light/static/autocomplete_light/autocomplete-light.css
autocomplete_light/static/autocomplete_light/autocomplete-light.js