Metadata-Version: 2.1
Name: autocomplete-light
Version: 1.1.5
Summary: simple autocompletion web component
Home-page: https://yourlabs.io/oss/autocomplete-light
Author: James Pic
Author-email: jamespic@gmail.com
License: MIT
Keywords: html autocomplete
Platform: UNKNOWN
Requires-Python: >=3.8
Provides-Extra: test
